sqlite_clean/__init__.py
sqlite_clean/__main__.py
sqlite_clean/catalog.py
sqlite_clean/command.py
sqlite_clean/constants.py
sqlite_clean/fix.py
sqlite_clean/lint.py
sqlite_clean/utils.py
sqlite_clean-0.0.4.dist-info/entry_points.txt
sqlite_clean-0.0.4.dist-info/LICENSE
sqlite_clean-0.0.4.dist-info/WHEEL
sqlite_clean-0.0.4.dist-info/METADATA
sqlite_clean-0.0.4.dist-info/RECORD
